collectmeteranalog/__init__.py
collectmeteranalog/__main__.py
collectmeteranalog/collect.py
collectmeteranalog/glob.py
collectmeteranalog/hash_manual.py
collectmeteranalog/labeling.py
collectmeteranalog/predict.py
collectmeteranalog/models/ana-class100_0157_s1_q.tflite
collectmeteranalog-1.0.16.dist-info/LICENSE
collectmeteranalog-1.0.16.dist-info/METADATA
collectmeteranalog-1.0.16.dist-info/WHEEL
collectmeteranalog-1.0.16.dist-info/top_level.txt
collectmeteranalog-1.0.16.dist-info/RECORD
