Metadata-Version: 2.1
Name: collectmeteranalog
Version: 1.0.16
Summary: Reads images from water meter pointers.
Home-page: https://github.com/haverland/collectmeteranalog
Author: Frank Haverland
Author-email: iotson@t-online.de
License: Apache 2.0
Keywords: different tags here
Platform: any
Classifier: Programming Language :: Python
Classifier: Development Status :: 4 - Beta
Classifier: Natural Language :: English
Classifier: Intended Audience :: Developers
Classifier: Operating System :: OS Independent
Classifier: Topic :: Software Development :: Libraries :: Application Frameworks
Classifier: Topic :: Internet :: WWW/HTTP :: Dynamic Content
License-File: LICENSE
Requires-Dist: pillow
Requires-Dist: numpy
Requires-Dist: matplotlib
Requires-Dist: scipy
Requires-Dist: scikit-learn
Requires-Dist: imagehash
Requires-Dist: urllib3
Requires-Dist: requests
Requires-Dist: pandas
Requires-Dist: importlib-metadata ; python_version == "3.9"
Requires-Dist: tflite-runtime ; sys_platform == "linux"
Requires-Dist: msvc-runtime ; sys_platform == "win32"
